tree_sitter_property_list/__init__.py
tree_sitter_property_list/__init__.pyi
tree_sitter_property_list/_binding.abi3.so
tree_sitter_property_list/binding.c
tree_sitter_property_list/py.typed
tree_sitter_property_list/queries/highlights.scm
tree_sitter_property_list-0.1.2.dist-info/licenses/LICENSE
tree_sitter_property_list-0.1.2.dist-info/METADATA
tree_sitter_property_list-0.1.2.dist-info/WHEEL
tree_sitter_property_list-0.1.2.dist-info/top_level.txt
tree_sitter_property_list-0.1.2.dist-info/RECORD
